funcgenialn-1.0.0.dist-info/licenses/LICENSE.txt
genialntools/__init__.py
genialntools/genial.py
funcgenialn-1.0.0.dist-info/METADATA
funcgenialn-1.0.0.dist-info/WHEEL
funcgenialn-1.0.0.dist-info/top_level.txt
funcgenialn-1.0.0.dist-info/RECORD
