Metadata-Version: 2.4
Name: FuncGenialn
Version: 1.0.0
Summary: A simple library for speed control in Python.
Home-page: https://github.com/nefoceo/genialtools
Author: NEFOR
Author-email: N7FOR8572@gmail.com
Classifier: Programming Language :: Python :: 3
Classifier: License :: OSI Approved :: MIT License
Classifier: Operating System :: OS Independent
Requires-Python: >=3.6
License-File: LICENSE.txt
Dynamic: author
Dynamic: author-email
Dynamic: classifier
Dynamic: description
Dynamic: description-content-type
Dynamic: home-page
Dynamic: license-file
Dynamic: requires-python
Dynamic: summary
